README.md
setup.cfg
setup.py
teebee/__about__.py
teebee/__init__.py
teebee/py.typed
teebee.egg-info/PKG-INFO
teebee.egg-info/SOURCES.txt
teebee.egg-info/dependency_links.txt
teebee.egg-info/not-zip-safe
teebee.egg-info/top_level.txt