Metadata-Version: 1.0
Name: teebee
Version: 0.1.4
Summary: 1k steps for 1 epoch in TensorBoard
Home-page: https://github.com/sublee/teebee
Author: Heungsub Lee
Author-email: sub@subl.ee
License: MIT
Platform: UNKNOWN
